{
  "db_name": "PostgreSQL",
  "query": "SELECT id, task_type, payload, is_read as \"is_read!\", created_at as \"created_at!\" \n         FROM notification_tasks WHERE is_read = false ORDER BY created_at DESC",
  "describe": {
    "columns": [
      {
        "ordinal": 0,
        "name": "id",
        "type_info": "Int4"
      },
      {
        "ordinal": 1,
        "name": "task_type",
        "type_info": "Varchar"
      },
      {
        "ordinal": 2,
        "name": "payload",
        "type_info": "Jsonb"
      },
      {
        "ordinal": 3,
        "name": "is_read!",
        "type_info": "Bool"
      },
      {
        "ordinal": 4,
        "name": "created_at!",
        "type_info": "Timestamptz"
      }
    ],
    "parameters": {
      "Left": []
    },
    "nullable": [
      false,
      false,
      true,
      true,
      true
    ]
  },
  "hash": "a045f8f1ab7884299395254908cbbc7176449a9ea37a50a114c87e23d35a828e"
}
